kpruss/__init__.py
kpruss/layout.html
kpruss/page.html
kpruss/post.html
kpruss/theme.conf
kpruss/static/custom.css
kpruss/static/email.svg
kpruss/static/github.svg
kpruss/static/kpruss.css_t
kpruss/static/linkedin.png
kpruss/static/stackoverflow.svg
kpruss/static/variables.css
kpruss-0.0.3.dist-info/LICENSE.rst
kpruss-0.0.3.dist-info/METADATA
kpruss-0.0.3.dist-info/WHEEL
kpruss-0.0.3.dist-info/entry_points.txt
kpruss-0.0.3.dist-info/top_level.txt
kpruss-0.0.3.dist-info/zip-safe
kpruss-0.0.3.dist-info/RECORD
