Metadata-Version: 2.1
Name: kpruss
Version: 0.0.3
Summary: The Sphinx theme for my website
Home-page: https://kprussing.github.io/kpruss/
Author: Keith F. Prussing
Author-email: kprussing74@gmail.com
License: UNKNOWN
Platform: UNKNOWN
Classifier: Development Status :: 1 - Planning
Classifier: Framework :: Sphinx :: Theme
Classifier: License :: OSI Approved :: BSD License
Classifier: Programming Language :: Python :: 3
Classifier: Programming Language :: Python :: 3.6
Classifier: Programming Language :: Python :: 3.7
Classifier: Programming Language :: Python :: 3.8
Classifier: Programming Language :: Python :: 3.9
Classifier: Programming Language :: Python :: 3 :: Only
Requires-Python: <4,>=3.6
Requires-Dist: sphinx (>=3.5)
